pmlops/__init__.py
pmlops/config.py
pmlops/inference.py
pmlops/observability.py
pmlops-0.3.0.dist-info/METADATA
pmlops-0.3.0.dist-info/WHEEL
pmlops-0.3.0.dist-info/RECORD
