Metadata-Version: 2.1
Name: pmlops
Version: 0.3.0
Summary: 
Author: Miguel Arquez
Author-email: miguel.arquez@ab-inbev.com
Requires-Python: >=3.9,<4.0
Classifier: Programming Language :: Python :: 3
Classifier: Programming Language :: Python :: 3.9
Classifier: Programming Language :: Python :: 3.10
Classifier: Programming Language :: Python :: 3.11
Requires-Dist: evidently (>=0.4.16,<0.5.0)
Requires-Dist: joblib (>=1.3.2,<2.0.0)
Requires-Dist: numpy (>=1.26.4,<2.0.0)
Requires-Dist: pandas (>=2.2.1,<3.0.0)
Requires-Dist: pydantic (>=2.6.3,<3.0.0)
Requires-Dist: scikit-learn (>=1.4.1.post1,<2.0.0)
